{"id": "Q102184594", "name": "Susan Nicolet Vineberg", "educatedAt": {"0": {"name": "University of California, Berkeley", "coordinates": {"latitude": 37.87, "longitude": -122.259, "altitude": null, "precision": 0.00027777777777778, "globe": "http://www.wikidata.org/entity/Q2"}}}, "occupation": {"0": "philosopher"}, "employer": {"0": {"name": "Wayne State University", "coordinates": {"latitude": 42.357344444444, "longitude": -83.070105555556, "altitude": null, "precision": 0.00027777777777778, "globe": "http://www.wikidata.org/entity/Q2"}}}}