{"id": "Q1157217", "name": "Dagfinn F\u00f8llesdal", "dateOfBirth": {"0": "+1932-06-22T00:00:00Z"}, "countryOfCitizenship": {"0": "Norway"}, "occupation": {"0": "philosopher", "1": "university teacher", "2": "researcher"}, "educatedAt": {"0": {"name": "Harvard University", "coordinates": {"latitude": 42.374443888889, "longitude": -71.116943888889, "altitude": null, "precision": 2.77778e-06, "globe": "http://www.wikidata.org/entity/Q2"}}, "1": {"name": "University of Oslo", "coordinates": {"latitude": 59.939936111111, "longitude": 10.722063888889, "altitude": null, "precision": 0.00027777777777778, "globe": "http://www.wikidata.org/entity/Q2"}}}, "employer": {"0": {"name": "Stanford University", "coordinates": {"latitude": 37.4275, "longitude": -122.17, "altitude": null, "precision": 0.0002777777777777778, "globe": "http://www.wikidata.org/entity/Q2"}}, "1": {"name": "University of Oslo", "coordinates": {"latitude": 59.939936111111, "longitude": 10.722063888889, "altitude": null, "precision": 0.00027777777777778, "globe": "http://www.wikidata.org/entity/Q2"}}}, "doctralStudent": {"0": "Hubert L. Dreyfus"}, "fieldOfWork": {"0": "philosophy", "1": "philosophy of language", "2": "phenomenology", "3": "existentialism", "4": "hermeneutics"}}