{"id": "Q1349785", "name": "Jean Beaufret", "countryOfCitizenship": {"0": "France"}, "educatedAt": {"0": {"name": "\u00c9cole Normale Sup\u00e9rieure", "coordinates": {"latitude": 48.841944444444, "longitude": 2.3444444444444, "altitude": null, "precision": 0.00027777777777778, "globe": "http://www.wikidata.org/entity/Q2"}}}, "dateOfBirth": {"0": "+1907-05-22T00:00:00Z"}, "dateOfDeath": {"0": "+1982-08-07T00:00:00Z"}, "occupation": {"0": "philosopher", "1": "historian", "2": "philosophy historian", "3": "French Resistance fighter"}, "employer": {"0": {"name": "Lyc\u00e9e Condorcet", "coordinates": {"latitude": 48.874722, "longitude": 2.327222, "altitude": null, "precision": 1e-06, "globe": "http://www.wikidata.org/entity/Q2"}}}}