{"id": "Q1364813", "name": "Norman Malcolm", "countryOfCitizenship": {"0": "United States of America"}, "dateOfBirth": {"0": "+1911-06-11T00:00:00Z"}, "dateOfDeath": {"0": "+1990-08-04T00:00:00Z"}, "educatedAt": {"0": {"name": "Harvard University", "coordinates": {"latitude": 42.374443888889, "longitude": -71.116943888889, "altitude": null, "precision": 2.77778e-06, "globe": "http://www.wikidata.org/entity/Q2"}}, "1": {"name": "University of Nebraska\u2013Lincoln", "coordinates": {"latitude": 40.8175, "longitude": -96.701388888889, "altitude": null, "precision": 0.00027777777777778, "globe": "http://www.wikidata.org/entity/Q2"}}}, "occupation": {"0": "philosopher", "1": "university teacher"}, "employer": {"0": {"name": "Cornell University", "coordinates": {"latitude": 42.447222222222, "longitude": -76.483055555556, "altitude": null, "precision": 0.00027777777777778, "globe": "http://www.wikidata.org/entity/Q2"}}}}