{"id": "Q19367451", "name": "Michael Wendler", "dateOfBirth": {"0": "+1610-09-21T00:00:00Z"}, "dateOfDeath": {"0": "+1671-11-21T00:00:00Z"}, "occupation": {"0": "theologian", "1": "university teacher", "2": "librarian", "3": "philosopher"}, "image": {"0": "Michael Wendeler.jpg"}, "studentOf": {"0": "Erasmus Schmidt", "1": "Ambrosius Rhode", "2": "Paul R\u00f6ber", "3": "Wilhelm Leyser", "4": "Johann H\u00fclsemann"}, "student": {"0": "Matthias Wasmuth"}, "employer": {"0": {"name": "University of Wittenberg", "coordinates": {"latitude": 51.864722, "longitude": 12.650278, "altitude": null, "precision": 0.00027777777777778, "globe": "http://www.wikidata.org/entity/Q2"}}}, "educatedAt": {"0": {"name": "University of Halle-Wittenberg", "coordinates": {"latitude": 51.48638889, "longitude": 11.96888889, "altitude": null, "precision": 0.00027777777777778, "globe": "http://www.wikidata.org/entity/Q2"}}}, "countryOfCitizenship": {"0": "Germany"}, "fieldOfWork": {"0": "theology", "1": "ethics"}, "edges": {"studentOf": {"0": {"id": "Q1679216", "name": "Jakob Martini"}}}}