{"id": "Q206119", "name": "Marcus Terentius Varro", "occupation": {"0": "writer", "1": "poet", "2": "music theorist", "3": "philosopher", "4": "Ancient Roman historian", "5": "grammarian", "6": "annalist", "7": "Ancient Roman military personnel"}, "countryOfCitizenship": {"0": "Ancient Rome"}, "timePeriod": {"0": "Roman Republic"}, "notableWork": {"0": "De lingua Latina", "1": "De re rustica"}, "image": {"0": "Statua di Marco Terenzio Varrone (Rieti) 02.jpg"}, "dateOfBirth": {"0": "-0116-00-00T00:00:00Z"}, "dateOfDeath": {"0": "-0027-00-00T00:00:00Z"}}