{"id": "Q2847489", "name": "Andr\u00e9 Chappert", "countryOfCitizenship": {"0": "France"}, "dateOfBirth": {"0": "+1953-01-01T00:00:00Z"}, "occupation": {"0": "philosopher", "1": "epistemologist", "2": "university teacher"}, "educatedAt": {"0": {"name": "University of Paris 1 Pantheon-Sorbonne", "coordinates": {"latitude": 48.848333, "longitude": 2.343056, "altitude": null, "precision": 1e-06, "globe": "http://www.wikidata.org/entity/Q2"}}}, "employer": {"0": {"name": "Paul-Val\u00e9ry-Montpellier University", "coordinates": {"latitude": 43.633, "longitude": 3.87, "altitude": null, "precision": 2.777777777778e-05, "globe": "http://www.wikidata.org/entity/Q2"}}}}