{"id": "Q3035015", "name": "Dominique Bourg", "dateOfBirth": {"0": "+1953-08-11T00:00:00Z"}, "countryOfCitizenship": {"0": "France", "1": "Switzerland"}, "occupation": {"0": "ecologist", "1": "honorary professor", "2": "politician", "3": "philosopher", "4": "university teacher"}, "employer": {"0": {"name": "University of Lausanne", "coordinates": {"latitude": 46.5225, "longitude": 6.5794444444444, "altitude": null, "precision": 0.00027777777777778, "globe": "http://www.wikidata.org/entity/Q2"}}, "1": {"name": "University of Technology of Troyes", "coordinates": {"latitude": 48.269155, "longitude": 4.067087, "altitude": null, "precision": 1e-06, "globe": "http://www.wikidata.org/entity/Q2"}}}, "educatedAt": {"0": {"name": "University of Strasbourg", "coordinates": {"latitude": 48.580277777778, "longitude": 7.7644444444444, "altitude": null, "precision": null, "globe": "http://www.wikidata.org/entity/Q2"}}, "1": {"name": "School for Advanced Studies in the Social Sciences", "coordinates": {"latitude": 48.83607, "longitude": 2.37205, "altitude": null, "precision": 1e-06, "globe": "http://www.wikidata.org/entity/Q2"}}}, "image": {"0": "Dominique Bourg, 2019 (cropped).jpg"}, "doctralStudent": {"0": "Cyril Adoue"}}