{"id": "Q3067194", "name": "Fathi Triki", "occupation": {"0": "philosopher"}, "dateOfBirth": {"0": "+1947-05-30T00:00:00Z"}, "educatedAt": {"0": {"name": "University of Paris 1 Pantheon-Sorbonne", "coordinates": {"latitude": 48.848333, "longitude": 2.343056, "altitude": null, "precision": 1e-06, "globe": "http://www.wikidata.org/entity/Q2"}}, "1": {"name": "University of Paris 1 Pantheon-Sorbonne", "coordinates": {"latitude": 48.848333, "longitude": 2.343056, "altitude": null, "precision": 1e-06, "globe": "http://www.wikidata.org/entity/Q2"}}}, "employer": {"0": {"name": "Tunis University", "coordinates": {"latitude": 36.797596481849745, "longitude": 10.162045354456572, "altitude": null, "precision": 1e-08, "globe": "http://www.wikidata.org/entity/Q2"}}}, "countryOfCitizenship": {"0": "French protectorate of Tunisia", "1": "Tunisia"}}