{"id": "Q326459", "name": "Dmitry Merezhkovsky", "countryOfCitizenship": {"0": "Russian Empire", "1": "Russia"}, "educatedAt": {"0": {"name": "Saint Petersburg State University", "coordinates": ""}}, "dateOfBirth": {"0": "+1865-08-02T00:00:00Z", "1": "+1866-08-02T00:00:00Z", "2": "+1865-00-00T00:00:00Z", "3": "+1865-08-14T00:00:00Z"}, "dateOfDeath": {"0": "+1941-12-09T00:00:00Z"}, "image": {"0": "Merezhkovskiy in NNovgorod.jpg"}, "occupation": {"0": "novelist", "1": "poet", "2": "literary critic", "3": "philosopher", "4": "writer", "5": "biographer", "6": "literary scholar", "7": "art historian"}, "movement": {"0": "Russian symbolism"}, "fieldOfWork": {"0": "philosophy"}}