{"id": "Q4094992", "name": "Valery Alekseievich Bosenko", "dateOfBirth": {"0": "+1927-01-01T00:00:00Z"}, "dateOfDeath": {"0": "+2007-03-19T00:00:00Z"}, "image": {"0": "Valerij Oleks.jpg"}, "occupation": {"0": "philosopher", "1": "university teacher"}, "countryOfCitizenship": {"0": "Soviet Union"}, "employer": {"0": {"name": "Taras Shevchenko National University of Kyiv", "coordinates": {"latitude": 50.441903, "longitude": 30.511314, "altitude": null, "precision": 1e-06, "globe": "http://www.wikidata.org/entity/Q2"}}}, "educatedAt": {"0": {"name": "Faculty of Philosophy, Taras Shevchenko National University Kyiv", "coordinates": ""}}}