{"id": "Q4178491", "name": "Yuri Zhdanov", "occupation": {"0": "chemist", "1": "university teacher", "2": "philosopher", "3": "polymath"}, "dateOfBirth": {"0": "+1919-08-20T00:00:00Z"}, "dateOfDeath": {"0": "+2006-12-19T00:00:00Z"}, "educatedAt": {"0": {"name": "MSU Faculty of Chemistry", "coordinates": {"latitude": 55.70222222, "longitude": 37.52583333, "altitude": null, "precision": 1e-05, "globe": "http://www.wikidata.org/entity/Q2"}}}, "countryOfCitizenship": {"0": "Soviet Union", "1": "Russia"}, "employer": {"0": {"name": "Southern Federal University", "coordinates": {"latitude": 47.2247, "longitude": 39.7286, "altitude": null, "precision": 2.77777777778e-06, "globe": "http://www.wikidata.org/entity/Q2"}}, "1": {"name": "Rostov State University", "coordinates": ""}}, "fieldOfWork": {"0": "chemistry", "1": "philosophy"}, "image": {"0": "\u0416\u0434\u0430\u043d\u043e\u0432 \u042e\u0440\u0438\u0439 \u0410\u043d\u0434\u0440\u0435\u0435\u0432\u0438\u0447.jpg"}, "doctralStudent": {"0": "Vladimir Minkin"}}