{"id": "Q4232349", "name": "Pawel Vasilievich Kopnin", "dateOfBirth": {"0": "+1922-01-27T00:00:00Z"}, "dateOfDeath": {"0": "+1971-06-27T00:00:00Z"}, "educatedAt": {"0": {"name": "Moscow University's Department of Philosophy", "coordinates": ""}}, "occupation": {"0": "philosopher", "1": "university teacher"}, "countryOfCitizenship": {"0": "Soviet Union", "1": "Ukrainian Soviet Socialist Republic"}, "employer": {"0": {"name": "Moscow State University", "coordinates": {"latitude": 55.7025, "longitude": 37.530555555556, "altitude": null, "precision": 0.00027777777777778, "globe": "http://www.wikidata.org/entity/Q2"}}}, "fieldOfWork": {"0": "philosophy"}}