{"id": "Q77057", "name": "Karl Robert Eduard von Hartmann", "countryOfCitizenship": {"0": "Kingdom of Prussia"}, "dateOfBirth": {"0": "+1842-02-23T00:00:00Z", "1": "+1842-01-01T00:00:00Z"}, "dateOfDeath": {"0": "+1906-06-05T00:00:00Z", "1": "+1906-01-01T00:00:00Z"}, "image": {"0": "Karl Robert Eduard von Hartmann (Photographic portrait).jpg"}, "occupation": {"0": "philosopher", "1": "writer"}, "educatedAt": {"0": {"name": "University of Rostock", "coordinates": {"latitude": 54.08813333333333, "longitude": 12.133372222222222, "altitude": null, "precision": 2.777777777777778e-06, "globe": "http://www.wikidata.org/entity/Q2"}}}, "fieldOfWork": {"0": "philosophy", "1": "psychology", "2": "pessimism", "3": "unconscious mind"}, "movement": {"0": "irrationalism"}, "edges": {"influencedBy": {"0": {"id": "Q9047", "name": "Gottfried Wilhelm Leibniz"}, "1": {"id": "Q38193", "name": "Arthur Schopenhauer"}, "2": {"id": "Q9235", "name": "Georg Wilhelm Friedrich Hegel"}, "3": {"id": "Q60070", "name": "Friedrich Wilhelm Joseph Schelling"}, "4": {"id": "Q1035", "name": "Charles Darwin"}}, "influenced": {"0": {"id": "Q76518", "name": "Hans Vaihinger"}}}}