{"id": "Q90586637", "name": "Simon Cullen", "occupation": {"0": "philosopher"}, "employer": {"0": {"name": "Carnegie Mellon University", "coordinates": {"latitude": 40.4425, "longitude": -79.94333333333333, "altitude": null, "precision": 0.0002777777777777778, "globe": "http://www.wikidata.org/entity/Q2"}}, "1": {"name": "Princeton University", "coordinates": {"latitude": 40.345277777778, "longitude": -74.656111111111, "altitude": null, "precision": 0.00027777777777778, "globe": "http://www.wikidata.org/entity/Q2"}}, "2": {"name": "Princeton University", "coordinates": {"latitude": 40.345277777778, "longitude": -74.656111111111, "altitude": null, "precision": 0.00027777777777778, "globe": "http://www.wikidata.org/entity/Q2"}}}, "educatedAt": {"0": {"name": "Princeton University", "coordinates": {"latitude": 40.345277777778, "longitude": -74.656111111111, "altitude": null, "precision": 0.00027777777777778, "globe": "http://www.wikidata.org/entity/Q2"}}}, "edges": {"studentOf": {"0": {"id": "Q18157771", "name": "Sarah-Jane Leslie"}, "1": {"id": "Q20732338", "name": "Gideon Rosen"}}}}