{"id": "Q1322939", "name": "John Peckham", "desc": "Archbishop of Canterbury", "wiki_link": "https://en.wikipedia.org/wiki/John_Peckham", "dateOfDeath": {"0": "+1292-12-08T00:00:00Z"}, "placeOfBirth": {"0": {"id": "Q246884", "name": "Lewes", "coordinates": {"latitude": 50.874722222222225, "longitude": 0.011666666666666665, "altitude": null, "precision": 0.0002777777777777778, "globe": "http://www.wikidata.org/entity/Q2"}}}, "placeOfDeath": {"0": {"id": "Q29303", "name": "Canterbury", "coordinates": {"latitude": 51.278333333333, "longitude": 1.0775, "altitude": null, "precision": 0.00027777777777778, "globe": "http://www.wikidata.org/entity/Q2"}}}, "occupation": {"0": {"id": "Q250867", "name": "Catholic priest"}, "1": {"id": "Q1234713", "name": "theologian"}, "2": {"id": "Q4964182", "name": "philosopher"}, "3": {"id": "Q36180", "name": "writer"}}, "dateOfBirth": {"0": "+1227-00-00T00:00:00Z"}, "studentOf": {"0": {"id": "Q43746", "name": "Bonaventure"}}, "student": {"0": {"id": "Q326307", "name": "Peter Olivi"}, "1": {"id": "Q718564", "name": "William de la Mare"}, "2": {"id": "Q2838721", "name": "Roger Marston"}}, "image": {"0": "Canterburycathedraljohnpeckhamtombeffigy.jpg"}, "priority": 0.09467455621301775}