{"id": "Q297040", "name": "Apollonius of Tyana", "desc": "1st century AD Greek Neopythagorean philosopher", "wiki_link": "https://en.wikipedia.org/wiki/Apollonius_of_Tyana", "dateOfBirth": {"0": "+0015-00-00T00:00:00Z"}, "dateOfDeath": {"0": "+0100-00-00T00:00:00Z"}, "occupation": {"0": "philosopher", "1": "mathematician"}, "image": {"0": "Apollonius of Tyana.jpg"}, "timePeriod": {"0": "High Roman Empire"}, "fieldOfWork": {"0": "philosophy"}, "movement": {"0": "neopythagoreanism"}, "influencedBy": {"0": "Pythagoras"}, "edges": {"influencedBy": {"0": {"id": "Q10261", "name": "Pythagoras"}}}}