{"id": "Q3113251", "name": "Graham Harman", "dateOfBirth": {"0": "+1968-05-09T00:00:00Z"}, "educatedAt": {"0": {"name": "Pennsylvania State University", "coordinates": {"latitude": 40.796111111111, "longitude": -77.862777777778, "altitude": null, "precision": 0.00027777777777778, "globe": "http://www.wikidata.org/entity/Q2"}}, "1": {"name": "DePaul University", "coordinates": {"latitude": 41.923558, "longitude": -87.653542, "altitude": null, "precision": 2.77777777778e-06, "globe": "http://www.wikidata.org/entity/Q2"}}, "2": {"name": "St. John's College", "coordinates": ""}}, "occupation": {"0": "philosopher", "1": "university teacher"}, "countryOfCitizenship": {"0": "United States of America"}, "image": {"0": "Graham Harman at MACBA.jpg"}, "employer": {"0": {"name": "The American University in Cairo", "coordinates": {"latitude": 30.019944444444, "longitude": 31.500344444444, "altitude": null, "precision": 0.00027777777777778, "globe": "http://www.wikidata.org/entity/Q2"}}, "1": {"name": "Southern California Institute of Architecture", "coordinates": {"latitude": 34.046, "longitude": -118.233, "altitude": null, "precision": 0.001, "globe": "http://www.wikidata.org/entity/Q2"}}}, "residence": {"0": {"name": "Mount Vernon", "coordinates": {"latitude": 41.924166666667, "longitude": -91.419722222222, "altitude": null, "precision": 0.00027777777777778, "globe": "http://www.wikidata.org/entity/Q2"}}, "1": {"name": "Dubuque", "coordinates": {"latitude": 42.504321, "longitude": -90.686865, "altitude": null, "precision": null, "globe": "http://www.wikidata.org/entity/Q2"}}, "2": {"name": "Cairo", "coordinates": {"latitude": 30.044444444444444, "longitude": 31.235833333333332, "altitude": null, "precision": 0.0002777777777777778, "globe": "http://www.wikidata.org/entity/Q2"}}, "3": {"name": "Ankara", "coordinates": {"latitude": 39.93576, "longitude": 32.83869, "altitude": null, "precision": 0.000277778, "globe": "http://www.wikidata.org/entity/Q2"}}, "4": {"name": "Los Angeles", "coordinates": {"latitude": 34.05223, "longitude": -118.24368, "altitude": null, "precision": 0.10842311330607, "globe": "http://www.wikidata.org/entity/Q2"}}}, "fieldOfWork": {"0": "philosophy", "1": "metaphysics", "2": "ontology"}}