{"id": "Q326624", "name": "V\u00e1clav \u010cern\u00fd", "countryOfCitizenship": {"0": "Czechoslovakia"}, "dateOfBirth": {"0": "+1905-03-26T00:00:00Z"}, "dateOfDeath": {"0": "+1987-07-02T00:00:00Z", "1": "+1987-01-27T00:00:00Z"}, "occupation": {"0": "philosopher", "1": "pedagogue", "2": "translator", "3": "writer", "4": "bohemicist", "5": "teacher", "6": "literary critic", "7": "literary historian", "8": "literary scholar", "9": "romanist", "10": "university teacher", "11": "literary scholar"}, "educatedAt": {"0": {"name": "Charles University", "coordinates": {"latitude": 50.0884, "longitude": 14.4037, "altitude": null, "precision": 0.014001065638779498, "globe": "http://www.wikidata.org/entity/Q2"}}, "1": {"name": "lyc\u00e9e Carnot", "coordinates": {"latitude": 47.3233, "longitude": 5.04833, "altitude": null, "precision": 2.7777777777778e-05, "globe": "http://www.wikidata.org/entity/Q2"}}, "2": {"name": "Faculty of Arts, Charles University in Prague", "coordinates": ""}, "3": {"name": "Examination Board for Teachers at Secondary Schools of Charles University", "coordinates": ""}}, "employer": {"0": {"name": "Faculty of Arts, Charles University in Prague", "coordinates": ""}, "1": {"name": "Charles University", "coordinates": {"latitude": 50.0884, "longitude": 14.4037, "altitude": null, "precision": 0.014001065638779498, "globe": "http://www.wikidata.org/entity/Q2"}}, "2": {"name": "University of Geneva", "coordinates": {"latitude": 46.19899, "longitude": 6.14446, "altitude": null, "precision": null, "globe": "http://www.wikidata.org/entity/Q2"}}, "3": {"name": "Masaryk University", "coordinates": {"latitude": 49.19861111111111, "longitude": 16.60527777777778, "altitude": null, "precision": 0.0002777777777777778, "globe": "http://www.wikidata.org/entity/Q2"}}}, "fieldOfWork": {"0": "literary studies", "1": "history of literature", "2": "literary criticism", "3": "Czech studies", "4": "Romance studies", "5": "philosophy", "6": "literature", "7": "translation", "8": "educational system"}, "edges": {"student": {"0": {"id": "Q12025432", "name": "Ji\u0159\u00ed Pechar"}}}}