{"id": "Q358561", "name": "Reinhold Niebuhr", "occupation": {"0": "theologian", "1": "university teacher", "2": "political scientist", "3": "philosopher", "4": "ethicist"}, "dateOfBirth": {"0": "+1892-06-21T00:00:00Z"}, "dateOfDeath": {"0": "+1971-06-01T00:00:00Z"}, "educatedAt": {"0": {"name": "Yale Divinity School", "coordinates": ""}, "1": {"name": "Eden Theological Seminary", "coordinates": {"latitude": 38.5927, "longitude": -90.3455, "altitude": null, "precision": 0.0001, "globe": "http://www.wikidata.org/entity/Q2"}}, "2": {"name": "Elmhurst University", "coordinates": {"latitude": 41.89611111, "longitude": -87.94611111, "altitude": null, "precision": 0.0003725094701816, "globe": "http://www.wikidata.org/entity/Q2"}}}, "influencedBy": {"0": "Karl Barth"}, "employer": {"0": {"name": "Union Theological Seminary", "coordinates": {"latitude": 40.811389, "longitude": -73.964167, "altitude": null, "precision": -1e-07, "globe": "http://www.wikidata.org/entity/Q2"}}}, "countryOfCitizenship": {"0": "United States of America"}, "fieldOfWork": {"0": "theology"}, "edges": {"influencedBy": {"0": {"id": "Q60104", "name": "Paul Tillich"}}, "influenced": {"0": {"id": "Q8027", "name": "Martin Luther King Jr."}, "1": {"id": "Q76326", "name": "Dietrich Bonhoeffer"}}}}