{"id": "Q358482", "name": "Eudemus of Rhodes", "occupation": {"0": "mathematician", "1": "astronomer", "2": "historian of mathematics", "3": "philosopher", "4": "historian of science", "5": "historian"}, "dateOfBirth": {"0": "-0370-01-01T00:00:00Z"}, "movement": {"0": "peripatetic school"}, "dateOfDeath": {"0": "-0300-00-00T00:00:00Z"}, "image": {"0": "Eudemos von Rhodos.jpg"}, "timePeriod": {"0": "Hellenistic period"}, "fieldOfWork": {"0": "philosophy"}, "countryOfCitizenship": {"0": "Rhodes"}, "edges": {"studentOf": {"0": {"id": "Q868", "name": "Aristotle"}}}}