{"id": "Q4055363", "name": "Sergey Avanesov", "dateOfBirth": {"0": "+1963-12-19T00:00:00Z"}, "countryOfCitizenship": {"0": "Soviet Union", "1": "Russia"}, "educatedAt": {"0": {"name": "Tomsk State University", "coordinates": {"latitude": 56.469515, "longitude": 84.947536, "altitude": null, "precision": 1e-06, "globe": "http://www.wikidata.org/entity/Q2"}}}, "employer": {"0": {"name": "Tomsk State University", "coordinates": {"latitude": 56.469515, "longitude": 84.947536, "altitude": null, "precision": 1e-06, "globe": "http://www.wikidata.org/entity/Q2"}}, "1": {"name": "Tomsk State Pedagogical University", "coordinates": {"latitude": 56.473889, "longitude": 84.976667, "altitude": null, "precision": 1e-06, "globe": "http://www.wikidata.org/entity/Q2"}}, "2": {"name": "Tomsk State University of Control Systems and Radio-electronics", "coordinates": ""}}, "fieldOfWork": {"0": "philosophy", "1": "religious studies"}, "image": {"0": "\u0410\u0432\u0430\u043d\u0435\u0441\u043e\u0432, \u0421\u0435\u0440\u0433\u0435\u0439 \u0421\u0435\u0440\u0433\u0435\u0435\u0432\u0438\u0447 2011.jpg"}, "occupation": {"0": "scientist"}}