{"id": "Q41513", "name": "William Blake", "desc": "English poet and artist (1757\u20131827)", "wiki_link": "https://en.wikipedia.org/wiki/William_Blake", "dateOfBirth": {"0": "+1757-11-28T00:00:00Z", "1": "+1757-01-01T00:00:00Z"}, "dateOfDeath": {"0": "+1827-08-12T00:00:00Z", "1": "+1827-01-01T00:00:00Z"}, "notableWork": {"0": {"id": "Q1132673", "name": "The Marriage of Heaven and Hell"}, "1": {"id": "Q489607", "name": "Jerusalem"}, "2": {"id": "Q630530", "name": "Songs of Innocence and of Experience"}, "3": {"id": "Q7909185", "name": "Vala, or The Four Zoas"}, "4": {"id": "Q6185194", "name": "Jerusalem The Emanation of the Giant Albion"}, "5": {"id": "Q6861538", "name": "Milton"}, "6": {"id": "Q2324840", "name": "The Ancient of Days"}}, "occupation": {"0": {"id": "Q1028181", "name": "painter"}, "1": {"id": "Q49757", "name": "poet"}, "2": {"id": "Q1234713", "name": "theologian"}, "3": {"id": "Q3243461", "name": "collector"}, "4": {"id": "Q11569986", "name": "printmaker"}, "5": {"id": "Q644687", "name": "illustrator"}, "6": {"id": "Q4964182", "name": "philosopher"}, "7": {"id": "Q16947657", "name": "lithographer"}, "8": {"id": "Q1925963", "name": "graphic artist"}, "9": {"id": "Q175151", "name": "printer"}, "10": {"id": "Q14623005", "name": "architectural draftsperson"}, "11": {"id": "Q36180", "name": "writer"}, "12": {"id": "Q1281618", "name": "sculptor"}, "13": {"id": "Q8178443", "name": "librettist"}}, "influencedBy": {"0": {"id": "Q101638", "name": "Mary Wollstonecraft"}, "1": {"id": "Q1067", "name": "Dante Alighieri"}, "2": {"id": "Q185832", "name": "Emmanuel Swedenborg"}, "3": {"id": "Q193857", "name": "Ben Jonson"}, "4": {"id": "Q77017", "name": "Jakob B\u00f6hme"}, "5": {"id": "Q79759", "name": "John Milton"}, "6": {"id": "Q8016608", "name": "William Pars"}, "7": {"id": "Q1042892", "name": "James Barry"}, "8": {"id": "Q215305", "name": "Giulio Romano"}, "9": {"id": "Q122382", "name": "Henry Fuseli"}}, "movement": {"0": {"id": "Q37068", "name": "Romanticism"}, "1": {"id": "Q2405999", "name": "fairy painting"}}, "studentOf": {"0": {"id": "Q18528667", "name": "Henry Pars"}, "1": {"id": "Q3656063", "name": "James Basire"}, "2": {"id": "Q1507897", "name": "George Michael Moser"}, "3": {"id": "Q1042892", "name": "James Barry"}}, "residence": {"0": {"id": "Q23662019", "name": "Green Street", "coordinates": ""}, "1": {"id": "Q4972570", "name": "Broadwick Street", "coordinates": {"latitude": 51.513611111111, "longitude": -0.13611111111111, "altitude": null, "precision": null, "globe": "http://www.wikidata.org/entity/Q2"}}, "2": {"id": "Q4972570", "name": "Broadwick Street", "coordinates": {"latitude": 51.513611111111, "longitude": -0.13611111111111, "altitude": null, "precision": null, "globe": "http://www.wikidata.org/entity/Q2"}}, "3": {"id": "Q23647169", "name": "Poland Street", "coordinates": {"latitude": 51.515708, "longitude": -0.137644, "altitude": null, "precision": 1e-06, "globe": "http://www.wikidata.org/entity/Q2"}}, "4": {"id": "Q23647494", "name": "Hercules Buildings", "coordinates": ""}, "5": {"id": "Q2227185", "name": "Felpham", "coordinates": {"latitude": 50.790461111111, "longitude": -0.65393888888889, "altitude": null, "precision": 0.00027777777777778, "globe": "http://www.wikidata.org/entity/Q2"}}, "6": {"id": "Q7567974", "name": "South Molton Street", "coordinates": {"latitude": 51.5136, "longitude": -0.147778, "altitude": null, "precision": 0.0001, "globe": "http://www.wikidata.org/entity/Q2"}}, "7": {"id": "Q23647819", "name": "Fountain Court", "coordinates": ""}, "8": {"id": "Q1138912", "name": "Battersea", "coordinates": {"latitude": 51.463769444444, "longitude": -0.16771111111111, "altitude": null, "precision": 0.00027777777777778, "globe": "http://www.wikidata.org/entity/Q2"}}, "9": {"id": "Q4972570", "name": "Broadwick Street", "coordinates": {"latitude": 51.513611111111, "longitude": -0.13611111111111, "altitude": null, "precision": null, "globe": "http://www.wikidata.org/entity/Q2"}}}, "educatedAt": {"0": {"id": "Q21579788", "name": "Royal Academy Schools", "coordinates": ""}, "1": {"id": "Q23661719", "name": "Henry Pars Drawing School", "coordinates": ""}}, "image": {"0": "William Blake by Thomas Phillips.jpg"}, "countryOfCitizenship": {"0": {"id": "Q174193", "name": "United Kingdom of Great Britain and Ireland"}, "1": {"id": "Q161885", "name": "Kingdom of Great Britain"}}, "student": {"0": {"id": "Q7794572", "name": "Thomas Trotter"}}, "fieldOfWork": {"0": {"id": "Q482", "name": "poetry"}}, "edges": {"influencedBy": {"0": {"id": "Q101638", "name": "Mary Wollstonecraft"}, "1": {"id": "Q1067", "name": "Dante Alighieri"}, "2": {"id": "Q185832", "name": "Emmanuel Swedenborg"}}, "influenced": {"0": {"id": "Q9204", "name": "C. S. Lewis"}}}, "priority": 0.7869822485207101}