{
	"id": "Q4295",
	"name": "Peter Abelard",
	"occupation": {
		"0": "theologian",
		"1": "philosopher",
		"2": "composer",
		"3": "linguist",
		"4": "poet",
		"5": "autobiographer",
		"6": "logician",
		"7": "writer",
		"8": "religious servant"
	},
	"countryOfCitizenship": {
		"0": "Kingdom of France",
		"1": "France"
	},
	"dateOfBirth": {
		"0": "+1079-01-01T00:00:00Z"
	},
	"educatedAt": {
		"0": {
			"name": "\u00c9cole cath\u00e9drale de Paris",
			"coordinates": ""
		}
	},
	"dateOfDeath": {
		"0": "+1142-04-21T00:00:00Z",
		"1": "+1142-00-00T00:00:00Z"
	},
	"movement": {
		"0": "Classical period",
		"1": "scholasticism",
		"2": "nominalism"
	},
	"student": {
		"0": "Hilarius",
		"1": "Berengar of Poitiers"
	},
	"image": {
		"0": "Abelard.jpg"
	},
	"fieldOfWork": {
		"0": "philosophy",
		"1": "scholasticism"
	},
	"notableWork": {
		"0": "Sic et Non",
		"1": "Dialectica"
	},
	"edges": {
		"student": {
			"0": {
				"id": "Q4313",
				"name": "Alain de Lille",
				"similarity": 0.2768688499927521
			},
			"1": {
				"id": "Q264028",
				"name": "John of Salisbury"
			},
			"2": {
				"id": "Q3436698",
				"name": "Robert of Melun"
			}
		},
		"studentOf": {
			"0": {
				"id": "Q297435",
				"name": "Roscellinus"
			},
			"1": {
				"id": "Q267825",
				"name": "William of Champeaux"
			}
		}
	}
}