{"id": "Q4604", "name": "Confucius", "desc": "Chinese philosopher and politician (551\u2013479 BCE)", "wiki_link": "https://en.wikipedia.org/wiki/Confucius", "occupation": {"0": {"id": "Q4964182", "name": "philosopher"}, "1": {"id": "Q37226", "name": "teacher"}, "2": {"id": "Q36180", "name": "writer"}}, "image": {"0": "Confucius, fresco from a Western Han tomb of Dongping County, Shandong province, China.jpg", "1": "Confucio saludo.JPG"}, "dateOfBirth": {"0": "-0552-10-09T00:00:00Z", "1": "-0551-10-04T00:00:00Z", "2": "-0551-00-00T00:00:00Z"}, "dateOfDeath": {"0": "-0479-03-09T00:00:00Z", "1": "-0479-00-00T00:00:00Z"}, "countryOfCitizenship": {"0": {"id": "Q736936", "name": "Lu"}}, "student": {"0": {"id": "Q836861", "name": "Zilu"}, "1": {"id": "Q1207671", "name": "Zengzi"}, "2": {"id": "Q1155960", "name": "Yan Hui"}, "3": {"id": "Q1039504", "name": "Duanmu Ci"}, "4": {"id": "Q11447909", "name": "Zhuansun Shi"}, "5": {"id": "Q837573", "name": "Zai Yu"}, "6": {"id": "Q840352", "name": "Ran Qiu"}, "7": {"id": "Q8193981", "name": "Ran Yong"}, "8": {"id": "Q24835307", "name": "Nh\u1ea1c Kh\u00e1i"}, "9": {"id": "Q24835393", "name": "\u4efb\u4e0d\u9f50"}, "10": {"id": "Q24834907", "name": "\u4f2f\u8654"}, "11": {"id": "Q10892588", "name": "Gongbo Liao"}, "12": {"id": "Q10892620", "name": "Gongye Chang"}, "13": {"id": "Q24835291", "name": "\u516c\u590f\u9996"}, "14": {"id": "Q10892833", "name": "Gongsun Long"}, "15": {"id": "Q10892972", "name": "Gongxi Ai"}, "16": {"id": "Q16903777", "name": "\u516c\u7956\u53e5\u5179"}, "17": {"id": "Q24835331", "name": "C\u00f4ng Ki\u00ean \u0110\u1ecbnh"}, "18": {"id": "Q6853486", "name": "\u516c\u826f\u5b7a"}, "19": {"id": "Q24835065", "name": "C\u00f4ng T\u00e2y D\u01b0 Nh\u01b0"}, "20": {"id": "Q24835069", "name": "C\u00f4ng T\u00e2y Ch\u00e2m"}, "21": {"id": "Q10893003", "name": "Gongxi Chi"}, "22": {"id": "Q24835041", "name": "\u5189\u5b63"}, "23": {"id": "Q24834934", "name": "\u5189\u5b7a"}, "24": {"id": "Q857146", "name": "Ran Geng"}, "25": {"id": "Q5363408", "name": "Nangong Kuo"}, "26": {"id": "Q24835267", "name": "Nguy\u00ean Kh\u00e1ng"}, "27": {"id": "Q10911249", "name": "Yuan Xian"}, "28": {"id": "Q24835319", "name": "\u53bf\u6210"}, "29": {"id": "Q12603391", "name": "Th\u00fac Tr\u1ecdng H\u1ed9i"}, "30": {"id": "Q24835981", "name": "C\u00e2u T\u1ec9nh C\u01b0\u01a1ng"}, "31": {"id": "Q10916692", "name": "\u53f8\u9a6c\u8015"}, "32": {"id": "Q24835142", "name": "Hou Chu"}, "33": {"id": "Q10923186", "name": "Th\u01b0\u01a1ng Tr\u1ea1ch"}, "34": {"id": "Q10923196", "name": "Shang Qu"}, "35": {"id": "Q24835146", "name": "Nh\u01b0\u1ee1ng T\u1ee9 X\u00edch"}, "36": {"id": "Q24835327", "name": "\u595a\u5bb9\u7bb4"}, "37": {"id": "Q10944085", "name": "Bu Shang"}, "38": {"id": "Q16159585", "name": "\u5b50\u8511"}, "39": {"id": "Q10948046", "name": "Fu Buqi"}, "40": {"id": "Q24835280", "name": "T\u1ea3 Nh\u00e2n D\u0129nh"}, "41": {"id": "Q11058327", "name": "Vu M\u00e3 Thi"}, "42": {"id": "Q24835311", "name": "\u5ec9\u7d5c"}, "43": {"id": "Q11085100", "name": "Thi Chi Th\u01b0\u1eddng"}, "44": {"id": "Q24834886", "name": "T\u00e0o Tu\u1ea5t"}, "45": {"id": "Q11091584", "name": "Zeng Dian"}, "46": {"id": "Q4533461", "name": "You Ruo"}, "47": {"id": "Q24834895", "name": "L\u01b0\u01a1ng Chi\u00ean"}, "48": {"id": "Q24835323", "name": "Vinh K\u1ef3"}, "49": {"id": "Q11121049", "name": "Xu Fan"}, "50": {"id": "Q24835138", "name": "\u6b69\u53d4\u4e57"}, "51": {"id": "Q16903788", "name": "Qidiao Kai"}, "52": {"id": "Q24835989", "name": "\u6f06\u96d5\u54c6"}, "53": {"id": "Q24835985", "name": "\u6f06\u96d5\u5f92\u7236"}, "54": {"id": "Q11566026", "name": "Tantai Mieming"}, "55": {"id": "Q24835261", "name": "Y\u1ebfn C\u1ea5p"}, "56": {"id": "Q24835256", "name": "Di Hei"}, "57": {"id": "Q24835365", "name": "\uc2e0\uc815 (\ucd98\ucd94)"}, "58": {"id": "Q24835057", "name": "Th\u1ea1ch T\u00e1c Th\u1ee5c"}, "59": {"id": "Q24835303", "name": "\u79e6\u5189"}, "60": {"id": "Q24835295", "name": "\u79e6\u5546"}, "61": {"id": "Q24835049", "name": "T\u1ea7n T\u1ed5"}, "62": {"id": "Q24835045", "name": "T\u1ea7n Phi"}, "63": {"id": "Q24835077", "name": "H\u00e3n Ph\u1ee5 H\u1eafc"}, "64": {"id": "Q8193964", "name": "Yan Yan"}, "65": {"id": "Q24835272", "name": "\u90a6\u5dfd"}, "66": {"id": "Q16259876", "name": "\u90d1\u90a6"}, "67": {"id": "Q24835129", "name": "\u9121\u55ae"}, "68": {"id": "Q698867", "name": "Min Sun"}, "69": {"id": "Q15926484", "name": "Yan Wuyou"}, "70": {"id": "Q24835285", "name": "Nhan Chi B\u1ed9c"}, "71": {"id": "Q24835276", "name": "Nhan H\u00e0"}, "72": {"id": "Q24835315", "name": "Nhan Kho\u00e1i"}, "73": {"id": "Q24834921", "name": "Nhan H\u1ea1nh"}, "74": {"id": "Q24835287", "name": "Nhan T\u1ed5"}, "75": {"id": "Q24835085", "name": "\uc548\uace0 (\ucd98\ucd94)"}, "76": {"id": "Q4505450", "name": "Gao Chai"}}, "movement": {"0": {"id": "Q9581", "name": "Confucianism"}}, "notableWork": {"0": {"id": "Q276015", "name": "Analects"}}, "fieldOfWork": {"0": {"id": "Q5891", "name": "philosophy"}, "1": {"id": "Q180592", "name": "social philosophy"}, "2": {"id": "Q9465", "name": "ethics"}}, "timePeriod": {"0": {"id": "Q185047", "name": "Spring and Autumn period"}}, "edges": {"influenced": {"0": {"id": "Q188903", "name": "Mencius"}, "1": {"id": "Q9047", "name": "Gottfried Wilhelm Leibniz"}, "2": {"id": "Q9068", "name": "Voltaire"}}, "taught": {"0": {"id": "Q8193981", "name": "Ran Yong"}}}, "priority": 0.8481262327416174}