{"id": "Q5345386", "name": "Edward Spencer Beesly", "dateOfDeath": {"0": "+1915-03-07T00:00:00Z"}, "dateOfBirth": {"0": "+1831-01-23T00:00:00Z"}, "countryOfCitizenship": {"0": "United Kingdom of Great Britain and Ireland"}, "occupation": {"0": "philosopher", "1": "university teacher"}, "image": {"0": "Edward Spencer Beesly National Portrait Gallery.jpeg"}, "employer": {"0": {"name": "Bedford College", "coordinates": {"latitude": 51.518545, "longitude": -0.129481, "altitude": null, "precision": 1e-06, "globe": "http://www.wikidata.org/entity/Q2"}}}, "educatedAt": {"0": {"name": "King William's College", "coordinates": {"latitude": 54.079722222222, "longitude": -4.6352777777778, "altitude": null, "precision": null, "globe": "http://www.wikidata.org/entity/Q2"}}}, "edges": {"studentOf": {"0": {"id": "Q473038", "name": "Richard Congreve"}}}}