{"id": "Q670103", "name": "Eino Kaila", "countryOfCitizenship": {"0": "Finland"}, "dateOfBirth": {"0": "+1890-08-09T00:00:00Z"}, "dateOfDeath": {"0": "+1958-07-31T00:00:00Z"}, "image": {"0": "Eino-Kaila-1951.jpg"}, "educatedAt": {"0": {"name": "University of Helsinki", "coordinates": {"latitude": 60.169444444444, "longitude": 24.95, "altitude": null, "precision": 0.00027777777777778, "globe": "http://www.wikidata.org/entity/Q2"}}, "1": {"name": "Helsinki Normal Lyceum", "coordinates": {"latitude": 60.162845, "longitude": 24.944009, "altitude": null, "precision": 1e-05, "globe": "http://www.wikidata.org/entity/Q2"}}}, "occupation": {"0": "philosopher", "1": "psychologist"}, "employer": {"0": {"name": "University of Helsinki", "coordinates": {"latitude": 60.169444444444, "longitude": 24.95, "altitude": null, "precision": 0.00027777777777778, "globe": "http://www.wikidata.org/entity/Q2"}}}, "residence": {"0": {"name": "Helsinki", "coordinates": {"latitude": 60.17556, "longitude": 24.93417, "altitude": null, "precision": 1e-05, "globe": "http://www.wikidata.org/entity/Q2"}}}, "fieldOfWork": {"0": "philosophy"}, "edges": {"student": {"0": {"id": "Q350183", "name": "Georg Henrik von Wright"}, "1": {"id": "Q11899797", "name": "Uuno Saarnio"}}}}