{"id": "Q840630", "name": "\u00c9lie Hal\u00e9vy", "educatedAt": {"0": {"name": "Lyc\u00e9e Condorcet", "coordinates": {"latitude": 48.874722, "longitude": 2.327222, "altitude": null, "precision": 1e-06, "globe": "http://www.wikidata.org/entity/Q2"}}, "1": {"name": "\u00c9cole Normale Sup\u00e9rieure", "coordinates": {"latitude": 48.841944444444, "longitude": 2.3444444444444, "altitude": null, "precision": 0.00027777777777778, "globe": "http://www.wikidata.org/entity/Q2"}}}, "dateOfBirth": {"0": "+1870-09-06T00:00:00Z"}, "dateOfDeath": {"0": "+1937-08-21T00:00:00Z"}, "countryOfCitizenship": {"0": "France"}, "occupation": {"0": "historian", "1": "philosopher"}, "image": {"0": "ElieHalevy.jpg"}, "fieldOfWork": {"0": "philosophy"}, "edges": {"studentOf": {"0": {"id": "Q2839759", "name": "Alphonse Darlu"}}}}