{"id": "Q954692", "name": "Eugenio Garin", "countryOfCitizenship": {"0": "Italy", "1": "Kingdom of Italy"}, "dateOfBirth": {"0": "+1909-05-09T00:00:00Z"}, "dateOfDeath": {"0": "+2004-12-29T00:00:00Z"}, "educatedAt": {"0": {"name": "University of Florence", "coordinates": {"latitude": 43.77777, "longitude": 11.25951, "altitude": null, "precision": 1e-05, "globe": "http://www.wikidata.org/entity/Q2"}}}, "employer": {"0": {"name": "University of Florence", "coordinates": {"latitude": 43.77777, "longitude": 11.25951, "altitude": null, "precision": 1e-05, "globe": "http://www.wikidata.org/entity/Q2"}}, "1": {"name": "Scuola Normale Superiore", "coordinates": {"latitude": 43.719611, "longitude": 10.400225, "altitude": null, "precision": 1e-06, "globe": "http://www.wikidata.org/entity/Q2"}}, "2": {"name": "University of Cagliari", "coordinates": {"latitude": 39.216944444444, "longitude": 9.115, "altitude": null, "precision": 0.00027777777777778, "globe": "http://www.wikidata.org/entity/Q2"}}}, "student": {"0": "Chiara Lefons"}, "occupation": {"0": "philosopher", "1": "philosophy historian", "2": "historian", "3": "university teacher"}, "edges": {"student": {"0": {"id": "Q3856556", "name": "Michele Ciliberto"}, "1": {"id": "Q3956192", "name": "Sergio Moravia"}}}}